pyspark_json_loader/__init__.py
pyspark_json_loader/main.py
pyspark_json_loader-0.1.7.dist-info/METADATA
pyspark_json_loader-0.1.7.dist-info/WHEEL
pyspark_json_loader-0.1.7.dist-info/top_level.txt
pyspark_json_loader-0.1.7.dist-info/RECORD
