Metadata-Version: 2.1
Name: pyspark-json-loader
Version: 0.1.7
Summary: A package to load and preprocess JSON data using PySpark
Home-page: https://github.com/AtifChaudary/pyspark-json-loader
Author: Chaudary Atif Raza Warraich
Author-email: atifr454@gmail.com
Classifier: Programming Language :: Python :: 3
Classifier: License :: OSI Approved :: MIT License
Classifier: Operating System :: OS Independent
Requires-Python: >=3.6
Requires-Dist: pyspark
Requires-Dist: py4j
